{
    "title": "Qcanvas使用文档",
    "description": "Qcanvas使用文档",
    "author": "lizhicheng",
    "output.name": "docs",
    "plugins": [
         "expandable-chapters-small",
         "tbfed-pagefooter",
         "code",
         "sidebar-style",
         "auto-scroll-table"
    ],
    "pluginsConfig": {
        "tbfed-pagefooter": {
          "copyright":"&copy Qcanvas",
          "modify_label": "文件修订时间：",
          "modify_format": "YYYY-MM-DD HH:mm:ss"
        },
        "sidebar-style": {
            "title": "前端开发",
            "author": "志成"
        }
    }
}